LICENSE.txt
README.md
usernado/__init__.py
usernado/api.py
usernado/base.py
usernado/errors.py
usernado/helpers.py
usernado/web.py
usernado/websocket.py
usernado-0.3.2.dist-info/LICENSE.txt
usernado-0.3.2.dist-info/WHEEL
usernado-0.3.2.dist-info/METADATA
usernado-0.3.2.dist-info/RECORD
