Metadata-Version: 2.1
Name: usernado
Version: 0.3.2
Summary: Makes it Easy to Manage Tornado Applications
Home-page: https://github.com/reganto/usernado
License: Apache-2.0
Keywords: Tornado,Python
Author: Reganto
Author-email: tell.reganto@gmail.com
Requires-Python: >=3.8,<4.0
Classifier: Environment :: Web Environment
Classifier: Intended Audience :: Developers
Classifier: License :: OSI Approved :: Apache Software License
Classifier: Operating System :: OS Independent
Classifier: Programming Language :: Python
Classifier: Programming Language :: Python :: 3
Classifier: Programming Language :: Python :: 3 :: Only
Classifier: Programming Language :: Python :: 3.10
Classifier: Programming Language :: Python :: 3.4
Classifier: Programming Language :: Python :: 3.5
Classifier: Programming Language :: Python :: 3.6
Classifier: Programming Language :: Python :: 3.7
Classifier: Programming Language :: Python :: 3.8
Classifier: Programming Language :: Python :: 3.9
Classifier: Topic :: Software Development :: Libraries :: Python Modules
Requires-Dist: pendulum (>=2.1.2,<3.0.0)
Requires-Dist: tornado-debugger (>=0.9.0,<0.10.0)
Project-URL: Bug Tracker, https://github.com/reganto/usernado/issues
Project-URL: Documentation, https://usernado.readthedocs.io/en/latest/
Project-URL: Repository, https://github.com/reganto/usernado
